api-connector/__init__.py
api-connector/main.py
base-api-connector/__init__.py
base-api-connector/main.py
base_api_connector/__init__.py
base_api_connector/base.py
base_api_connector/example.py
base_api_connector/main.py
base_api_connector-0.3.1.1.dist-info/LICENSE
base_api_connector-0.3.1.1.dist-info/METADATA
base_api_connector-0.3.1.1.dist-info/WHEEL
base_api_connector-0.3.1.1.dist-info/top_level.txt
base_api_connector-0.3.1.1.dist-info/RECORD
