Metadata-Version: 2.1
Name: base-api-connector
Version: 0.3.1.1
Summary: Generic Connector so you can easily create simple and readable classes for accessing APIs.
Home-page: https://github.com/I-K0haku-I/base-api-connector
Author: Andreas Schäfer
License: UNKNOWN
Platform: UNKNOWN
Requires-Dist: requests
Requires-Dist: aiohttp
